quality_prompts/__init__.py
quality_prompts/exemplars.py
quality_prompts/prompt.py
quality_prompts/utils/__init__.py
quality_prompts/utils/llm.py
quality_prompts/utils/prompt_postprocessing.py
quality_prompts/utils/prompting_techniques_system_prompts.py
quality_prompts-0.0.5.dist-info/LICENSE
quality_prompts-0.0.5.dist-info/METADATA
quality_prompts-0.0.5.dist-info/WHEEL
quality_prompts-0.0.5.dist-info/top_level.txt
quality_prompts-0.0.5.dist-info/RECORD
