Metadata-Version: 2.1
Name: quality-prompts
Version: 0.0.5
License-File: LICENSE
Requires-Dist: litellm (==1.41.8)
